django_dbaccounting/__init__.py
django_dbaccounting/admin.py
django_dbaccounting/apps.py
django_dbaccounting/forms.py
django_dbaccounting/models.py
django_dbaccounting/urls.py
django_dbaccounting/views.py
django_dbaccounting/migrations/0001_initial.py
django_dbaccounting/migrations/0002_auto_20200303_2358.py
django_dbaccounting/migrations/0003_auto_20200304_0000.py
django_dbaccounting/migrations/0004_auto_20200305_0001.py
django_dbaccounting/migrations/0005_accounttype_parent.py
django_dbaccounting/migrations/0006_account_date_create.py
django_dbaccounting/migrations/0007_auto_20200306_2118.py
django_dbaccounting/migrations/0008_transaction_updating.py
django_dbaccounting/migrations/0009_transaction_edited.py
django_dbaccounting/migrations/0010_auto_20200307_1933.py
django_dbaccounting/migrations/__init__.py
django_dbaccounting/tests/__init__.py
django_dbaccounting/tests/test_forms.py
django_dbaccounting/tests/test_models.py
django_dbaccounting/tests/test_views.py
migrations/0001_initial.py
migrations/0002_auto_20200303_2358.py
migrations/0003_auto_20200304_0000.py
migrations/0004_auto_20200305_0001.py
migrations/0005_accounttype_parent.py
migrations/0006_account_date_create.py
migrations/0007_auto_20200306_2118.py
migrations/0008_transaction_updating.py
migrations/0009_transaction_edited.py
migrations/0010_auto_20200307_1933.py
migrations/__init__.py
tests/__init__.py
tests/test_forms.py
tests/test_models.py
tests/test_views.py
django_dbaccounting-0.3.dist-info/LICENSE
django_dbaccounting-0.3.dist-info/LICENSE.txt
django_dbaccounting-0.3.dist-info/METADATA
django_dbaccounting-0.3.dist-info/WHEEL
django_dbaccounting-0.3.dist-info/top_level.txt
django_dbaccounting-0.3.dist-info/RECORD
